sinapsis_zonos/__init__.py
sinapsis_zonos/helpers/__init__.py
sinapsis_zonos/helpers/tags.py
sinapsis_zonos/helpers/zonos_keys.py
sinapsis_zonos/helpers/zonos_tts_utils.py
sinapsis_zonos/templates/__init__.py
sinapsis_zonos/templates/zonos_tts.py
sinapsis_zonos-0.1.10.dist-info/licenses/LICENSE
sinapsis_zonos-0.1.10.dist-info/METADATA
sinapsis_zonos-0.1.10.dist-info/WHEEL
sinapsis_zonos-0.1.10.dist-info/top_level.txt
sinapsis_zonos-0.1.10.dist-info/RECORD
