Metadata-Version: 2.4
Name: sinapsis-zonos
Version: 0.1.10
Summary: Text to speech using the Zonos model
Author-email: SinapsisAI <dev@sinapsis.tech>
Project-URL: Homepage, https://sinapsis.tech
Project-URL: Documentation, https://docs.sinapsis.tech/docs
Project-URL: Tutorials, https://docs.sinapsis.tech/tutorials
Project-URL: Repository, https://github.com/Sinapsis-AI/sinapsis-speech.git
Requires-Python: >=3.10
License-File: LICENSE
Requires-Dist: sinapsis>=0.1.1
Requires-Dist: zonos>=0.1.1
Provides-Extra: data-tools
Requires-Dist: sinapsis-data-readers>=0.1.2; extra == "data-tools"
Provides-Extra: all
Requires-Dist: sinapsis-zonos[data-tools]; extra == "all"
Dynamic: license-file
